verbum/__init__.py
verbum/api/__init__.py
verbum/api/main.py
verbum/api/models.py
verbum/cli/__init__.py
verbum/cli/main.py
verbum/core/__init__.py
verbum/core/bible_service.py
verbum/core/factory.py
verbum/core/normalizer.py
verbum/data/ACV.json
verbum/data/KJV.json
verbum/domain/__init__.py
verbum/domain/reference.py
verbum/infrastructure/__init__.py
verbum/infrastructure/repositories/__init__.py
verbum/infrastructure/repositories/bible_repository.py
verbum/infrastructure/repositories/json_bible_repository.py
verbum/test/__init__.py
verbum/test/test_cli_flow.py
verbum/test/test_reference.py
verbum_cli-0.3.0.dist-info/METADATA
verbum_cli-0.3.0.dist-info/WHEEL
verbum_cli-0.3.0.dist-info/entry_points.txt
verbum_cli-0.3.0.dist-info/top_level.txt
verbum_cli-0.3.0.dist-info/RECORD
