Metadata-Version: 2.4
Name: verbum-cli
Version: 0.3.0
Summary: Verbum is a Rich-powered command-line and API tool for reading, searching, and exploring the Bible interactively.
Author-email: Jhans Oscar <jhansoscar@icloud.com>
License-Expression: MIT
Project-URL: Homepage, https://github.com/jhans-oscar/verbum
Project-URL: Repository, https://github.com/jhans-oscar/verbum
Keywords: bible,cli,scripture,terminal,rich
Classifier: Programming Language :: Python :: 3
Classifier: Operating System :: OS Independent
Classifier: Environment :: Console
Classifier: Intended Audience :: End Users/Desktop
Classifier: Topic :: Utilities
Requires-Python: >=3.10
Requires-Dist: fastapi>=0.110
Requires-Dist: pydantic>=2.7
Requires-Dist: uvicorn>=0.23
Requires-Dist: rich>=13.0
Requires-Dist: pytest>=8.0
